user_external_local/__init__.py
user_external_local/token__user_external.py
user_external_local/user_externals_local.py
user_external_local-0.0.158.dist-info/METADATA
user_external_local-0.0.158.dist-info/WHEEL
user_external_local-0.0.158.dist-info/top_level.txt
user_external_local-0.0.158.dist-info/RECORD
