Metadata-Version: 2.4
Name: user-external-local
Version: 0.0.158
Home-page: https://github.com/circles-zone/user-external-local-python-package
Author: Circles
Author-email: info@circles.life
Classifier: Programming Language :: Python :: 3
Classifier: Operating System :: OS Independent
Requires-Dist: logger-local>=0.0.61
Requires-Dist: database-mysql-local>=0.0.83
Requires-Dist: python-sdk-remote>=0.0.64
Requires-Dist: user-context-remote>=0.0.54
Requires-Dist: database-infrastructure-local>=0.0.23
Dynamic: author
Dynamic: author-email
Dynamic: classifier
Dynamic: description
Dynamic: description-content-type
Dynamic: home-page
Dynamic: requires-dist
